docs/conf.py
docs/contributing.rst
docs/index.rst
docs/installation.rst
simularium_metrics_calculator/__init__.py
simularium_metrics_calculator/constants.py
simularium_metrics_calculator/exceptions.py
simularium_metrics_calculator/metric_info.py
simularium_metrics_calculator/metrics_registry.py
simularium_metrics_calculator/metrics_service.py
simularium_metrics_calculator/plot_info.py
simularium_metrics_calculator/py.typed
simularium_metrics_calculator/bin/example.py
simularium_metrics_calculator/calculators/__init__.py
simularium_metrics_calculator/calculators/agents_calculator.py
simularium_metrics_calculator/calculators/calculator.py
simularium_metrics_calculator/calculators/nearest_neighbor_calculator.py
simularium_metrics_calculator/calculators/number_of_agents_calculator.py
simularium_metrics_calculator/calculators/times_calculator.py
simularium_metrics_calculator/tests/__init__.py
simularium_metrics_calculator/tests/conftest.py
simularium_metrics_calculator/tests/test_add_plot.py
simularium_metrics_calculator/tests/test_available_metrics.py
simularium_metrics_calculator/tests/test_nearest_neighbor.py
simularium_metrics_calculator/tests/test_number_of_agents.py
simularium_metrics_calculator/tests/data/aster_pull3D_couples_actin_solid_3_frames_small.json
simularium_metrics_calculator-1.0.2.dist-info/LICENSE
simularium_metrics_calculator-1.0.2.dist-info/METADATA
simularium_metrics_calculator-1.0.2.dist-info/WHEEL
simularium_metrics_calculator-1.0.2.dist-info/top_level.txt
simularium_metrics_calculator-1.0.2.dist-info/RECORD
