Metadata-Version: 2.1
Name: simularium-metrics-calculator
Version: 1.0.2
Summary: Calculate plot metrics from spatial agent data
Author-email: Blair Lyons <blair208@gmail.com>
License: Apache Software License 2.0
Project-URL: Homepage, https://github.com/simularium/metrics-calculator
Project-URL: Bug Tracker, https://github.com/simularium/metrics-calculator/issues
Project-URL: Documentation, https://simularium.github.io/metrics-calculator
Project-URL: User Support, https://github.com/simularium/metrics-calculator/issues
Classifier: Development Status :: 4 - Beta
Classifier: Natural Language :: English
Classifier: Programming Language :: Python :: 3.8
Classifier: Programming Language :: Python :: 3.9
Classifier: Programming Language :: Python :: 3.10
Requires-Python: >=3.8
License-File: LICENSE
Requires-Dist: simulariumio
Requires-Dist: scipy
Provides-Extra: dev
Requires-Dist: ipython (>=8.4.0) ; extra == 'dev'
Provides-Extra: docs
Requires-Dist: m2r2 (>=0.2.7) ; extra == 'docs'
Requires-Dist: Sphinx (>=4.0.0) ; extra == 'docs'
Requires-Dist: furo (>=2022.4.7) ; extra == 'docs'
Requires-Dist: numpydoc ; extra == 'docs'
Requires-Dist: sphinx-copybutton ; extra == 'docs'
Requires-Dist: docutils (<0.19,>=0.18) ; extra == 'docs'
Provides-Extra: lint
Requires-Dist: black (>=22.3.0) ; extra == 'lint'
Requires-Dist: check-manifest (>=0.48) ; extra == 'lint'
Requires-Dist: flake8 (>=3.8.3) ; extra == 'lint'
Requires-Dist: flake8-debugger (>=3.2.1) ; extra == 'lint'
Requires-Dist: flake8-pyprojecttoml (==0.0.1) ; extra == 'lint'
Requires-Dist: flake8-typing-imports (>=1.9.0) ; extra == 'lint'
Requires-Dist: isort (>=5.7.0) ; extra == 'lint'
Requires-Dist: mypy (>=0.790) ; extra == 'lint'
Requires-Dist: pre-commit (>=2.20.0) ; extra == 'lint'
Provides-Extra: test
Requires-Dist: coverage (>=5.1) ; extra == 'test'
Requires-Dist: pytest (>=5.4.3) ; extra == 'test'
Requires-Dist: pytest-cov (>=2.9.0) ; extra == 'test'
Requires-Dist: pytest-raises (>=0.11) ; extra == 'test'
